[
      {
        "_id": "6334217d32007ab13fdff212",
        "price": 466,
        "name": "Lina Berry Mccoy",
        "company": "OTHERWAY"
      },
      {
        "_id": "6334217d399b09fec491a308",
        "price": 167,
        "name": "Carmella Potter",
        "company": "CRUSTATIA"
      },
      {
        "_id": "6334217d6f7ee2ef5130c463",
        "price": 644,
        "name": "Ortega Romero",
        "company": "ECSTASIA"
      },
      {
        "_id": "6334217d417e43660620c5c6",
        "price": 63,
        "name": "Holman Moran",
        "company": "ZENTRY"
      },
      {
        "_id": "6334217d04b4e2beb7372432",
        "price": 606,
        "name": "Selma Blackwell",
        "company": "SYBIXTEX"
      },
      {
        "_id": "6334217d444dbd29b18809cc",
        "price": 273,
        "name": "Acosta Castaneda",
        "company": "ZYTRAX"
      }
    ]